annex4ac/__init__.py
annex4ac/annex4ac.py
annex4ac/config.py
annex4ac/constants.py
annex4ac/db.py
annex4ac/docx_generator.py
annex4ac/lic_pub.pem
annex4ac/tags.py
annex4ac/fonts/LiberationSans-Bold.ttf
annex4ac/fonts/LiberationSans-Regular.ttf
annex4ac/fonts/OFL.txt
annex4ac/fonts/__init__.py
annex4ac/policy/__init__.py
annex4ac/policy/annex4ac_validate.py
annex4ac/resources/__init__.py
annex4ac/resources/high_risk_tags.default.json
annex4ac/resources/sRGB.icc
annex4ac/templates/template.html
annex4ac-1.4.5.dist-info/licenses/LICENSE
annex4ac-1.4.5.dist-info/licenses/THIRD_PARTY_LICENSES.md
annex4ac-1.4.5.dist-info/licenses/annex4ac/fonts/OFL.txt
annex4ac-1.4.5.dist-info/METADATA
annex4ac-1.4.5.dist-info/WHEEL
annex4ac-1.4.5.dist-info/entry_points.txt
annex4ac-1.4.5.dist-info/top_level.txt
annex4ac-1.4.5.dist-info/RECORD
