Metadata-Version: 2.4
Name: annex4ac
Version: 1.4.5
Summary: Annex IV-as-Code CLI: generate & validate EU AI Act Annex IV with legal compliance
Author-email: Aleksandr Racionalus <prihodko02bk@gmail.com>
License-Expression: MIT
Keywords: AI Act,compliance,CLI
Requires-Python: >=3.9
License-File: LICENSE
License-File: THIRD_PARTY_LICENSES.md
License-File: annex4ac/fonts/OFL.txt
Requires-Dist: typer[all]>=0.12
Requires-Dist: pydantic>=2.7
Requires-Dist: requests>=2.32
Requires-Dist: ruamel.yaml>=0.18
Requires-Dist: beautifulsoup4>=4.12
Requires-Dist: PyYAML>=6.0
Requires-Dist: Jinja2>=3.0
Requires-Dist: reportlab>=4.0
Requires-Dist: pyjwt<2.10,>=2.9
Requires-Dist: cryptography>=42
Requires-Dist: python-docx>=1.1
Requires-Dist: ftfy>=6.0
Requires-Dist: pikepdf>=8.0
Requires-Dist: SQLAlchemy>=2.0
Requires-Dist: psycopg[binary]>=3.1
Requires-Dist: pydantic-settings>=2
Requires-Dist: python-dateutil>=2.9
Requires-Dist: platformdirs>=4.0
Dynamic: license-file
